manifestparser/__init__.py
manifestparser/cli.py
manifestparser/expression.py
manifestparser/filters.py
manifestparser/ini.py
manifestparser/manifestparser.py
manifestparser/util.py
manifestparser-2.1.0.dist-info/DESCRIPTION.rst
manifestparser-2.1.0.dist-info/METADATA
manifestparser-2.1.0.dist-info/RECORD
manifestparser-2.1.0.dist-info/WHEEL
manifestparser-2.1.0.dist-info/entry_points.txt
manifestparser-2.1.0.dist-info/metadata.json
manifestparser-2.1.0.dist-info/top_level.txt
