Metadata-Version: 2.0
Name: manifestparser
Version: 2.1.0
Summary: Library to create and manage test manifests
Home-page: https://wiki.mozilla.org/Auto-tools/Projects/Mozbase
Author: Mozilla Automation and Testing Team
Author-email: tools@lists.mozilla.org
License: MPL
Keywords: mozilla manifests
Platform: UNKNOWN
Classifier: Programming Language :: Python :: 2.7
Classifier: Programming Language :: Python :: 3
Classifier: Programming Language :: Python :: 3.5
Requires-Dist: mozlog (>=6.0)
Requires-Dist: six (>=1.10.0)
